weaviate_txtai/__init__.py
weaviate_txtai/client.py
weaviate_txtai-0.1.0a3.dist-info/WHEEL
weaviate_txtai-0.1.0a3.dist-info/METADATA
weaviate_txtai-0.1.0a3.dist-info/RECORD
