Metadata-Version: 2.1
Name: weaviate-txtai
Version: 0.1.0a3
Summary: An integration of the weaviate vector search engine with txtai
Author: hsm207
Author-email: hsm207@users.noreply.github.com
Requires-Python: >=3.8,<4.0
Classifier: Development Status :: 3 - Alpha
Classifier: Intended Audience :: Developers
Classifier: License :: OSI Approved :: BSD License
Classifier: Programming Language :: Python :: 3
Classifier: Programming Language :: Python :: 3.8
Classifier: Programming Language :: Python :: 3.9
Classifier: Programming Language :: Python :: 3.10
Classifier: Programming Language :: Python :: 3.11
Classifier: Topic :: Database :: Database Engines/Servers
Classifier: Topic :: Scientific/Engineering :: Artificial Intelligence
Requires-Dist: txtai[api] (>=5.1.0,<6.0.0)
Requires-Dist: weaviate-client (>=3.9.0,<4.0.0)
